{
  "schema_version": "1.0",
  "generated_at": "2026-06-01T14:52:10.274893+00:00",
  "data_mode": "public_demo",
  "source_categories": [
    "OPEN_DATA",
    "HYBRID_OPEN_SYNTHETIC"
  ],
  "lineage": [
    {
      "source_id": "ahs_public_wait_times",
      "category": "OPEN_DATA",
      "freshness_state": "synthetic fallback current",
      "quality_score": 1.0,
      "activation_status": "public fallback"
    },
    {
      "source_id": "hqca_ed_metrics",
      "category": "OPEN_DATA",
      "freshness_state": "synthetic fallback current",
      "quality_score": 1.0,
      "activation_status": "public fallback"
    },
    {
      "source_id": "alberta_respiratory_dashboard",
      "category": "OPEN_DATA",
      "freshness_state": "synthetic fallback current",
      "quality_score": 1.0,
      "activation_status": "public fallback"
    },
    {
      "source_id": "eccc_geomet_weather_alerts",
      "category": "OPEN_DATA",
      "freshness_state": "synthetic fallback current",
      "quality_score": 1.0,
      "activation_status": "public fallback"
    },
    {
      "source_id": "alberta_aqhi",
      "category": "OPEN_DATA",
      "freshness_state": "synthetic fallback current",
      "quality_score": 1.0,
      "activation_status": "public fallback"
    },
    {
      "source_id": "alberta_wildfire",
      "category": "OPEN_DATA",
      "freshness_state": "synthetic fallback current",
      "quality_score": 1.0,
      "activation_status": "public fallback"
    },
    {
      "source_id": "alberta_511_events",
      "category": "OPEN_DATA",
      "freshness_state": "synthetic fallback current",
      "quality_score": 1.0,
      "activation_status": "public fallback"
    },
    {
      "source_id": "municipal_open_data_traffic",
      "category": "OPEN_DATA",
      "freshness_state": "synthetic fallback current",
      "quality_score": 1.0,
      "activation_status": "early feasible"
    },
    {
      "source_id": "calgary_transit_gtfs",
      "category": "OPEN_DATA",
      "freshness_state": "synthetic fallback current",
      "quality_score": 1.0,
      "activation_status": "early feasible"
    },
    {
      "source_id": "alberta_general_holidays",
      "category": "OPEN_DATA",
      "freshness_state": "synthetic fallback current",
      "quality_score": 1.0,
      "activation_status": "public fallback"
    },
    {
      "source_id": "tb_ed_visits",
      "category": "SECURE_INTERNAL_READY_SCHEMA",
      "freshness_state": "internal-ready schema",
      "quality_score": 0.0,
      "activation_status": "Snowflake day-one ready"
    },
    {
      "source_id": "chart_review_semantic_views",
      "category": "SECURE_INTERNAL_READY_SCHEMA",
      "freshness_state": "internal-ready schema",
      "quality_score": 0.0,
      "activation_status": "Snowflake day-one ready"
    }
  ],
  "synthetic_flag": true,
  "caveats": [
    "Public artifact: open-data-shaped and synthetic demonstration values only.",
    "No patient-level data, secure AHS data, or private endpoints are included."
  ],
  "payload": {
    "what_changed": "The public showcase separates open/synthetic demonstration from secure internal action intelligence.",
    "why_it_changed": "Colleague-portable AHS work needs a protected Streamlit/Snowflake path and a separate public narrative.",
    "confidence": "high on architecture boundary; model confidence requires internal validation",
    "improved": [
      "clearer public/internal boundary",
      "reusable kernel",
      "Snowflake activation map"
    ],
    "worsened": [
      "public showcase cannot display real operational truth"
    ],
    "bottleneck_moved_to": "governed internal data activation",
    "watch_points": [
      "lineage",
      "RBAC",
      "model validation",
      "identifier handling"
    ],
    "operational_levers": [
      "activate TB_ED_VISITS features",
      "curate secure operational feeds",
      "validate before pilot"
    ],
    "validation_needed": [
      "Snowflake holdout validation",
      "facility calibration",
      "privacy review"
    ],
    "limitations": [
      "synthetic values",
      "no real-time internal feeds",
      "no clinical automation"
    ],
    "huddle_brief": [
      "Use the showcase for vision, not operations.",
      "Use Action Intelligence inside governed Snowflake for internal testing.",
      "Keep identifiers and chart context inside secure views.",
      "Validate models before workflow change.",
      "Human leaders remain accountable for decisions."
    ]
  }
}